komand/__init__.py
komand/action.py
komand/cli.py
komand/connection.py
komand/dispatcher.py
komand/exceptions.py
komand/helper.py
komand/plugin.py
komand/schema.py
komand/server.py
komand/step.py
komand/trigger.py
komand/util.py
komand/variables.py
komand/data/input_message_schema.json
komand/data/output_message_schema.json
tests/__init__.py
tests/plugin/__init__.py
tests/plugin/hello_world/__init__.py
tests/plugin/hello_world/hello_world/__init__.py
tests/plugin/hello_world/hello_world/setup.py
tests/plugin/hello_world/hello_world/komand_hello_world/__init__.py
tests/plugin/hello_world/hello_world/komand_hello_world/actions/__init__.py
tests/plugin/hello_world/hello_world/komand_hello_world/actions/hello/__init__.py
tests/plugin/hello_world/hello_world/komand_hello_world/actions/hello/action.py
tests/plugin/hello_world/hello_world/komand_hello_world/actions/hello/schema.py
tests/plugin/hello_world/hello_world/komand_hello_world/actions/return_bad_json/__init__.py
tests/plugin/hello_world/hello_world/komand_hello_world/actions/return_bad_json/action.py
tests/plugin/hello_world/hello_world/komand_hello_world/actions/return_bad_json/schema.py
tests/plugin/hello_world/hello_world/komand_hello_world/actions/throw_exception/__init__.py
tests/plugin/hello_world/hello_world/komand_hello_world/actions/throw_exception/action.py
tests/plugin/hello_world/hello_world/komand_hello_world/actions/throw_exception/schema.py
tests/plugin/hello_world/hello_world/komand_hello_world/connection/__init__.py
tests/plugin/hello_world/hello_world/komand_hello_world/connection/connection.py
tests/plugin/hello_world/hello_world/komand_hello_world/connection/schema.py
tests/plugin/hello_world/hello_world/komand_hello_world/triggers/__init__.py
tests/plugin/hello_world/hello_world/komand_hello_world/triggers/hello_trigger/__init__.py
tests/plugin/hello_world/hello_world/komand_hello_world/triggers/hello_trigger/schema.py
komand-3.2.0.dist-info/METADATA
komand-3.2.0.dist-info/WHEEL
komand-3.2.0.dist-info/top_level.txt
komand-3.2.0.dist-info/RECORD
