Metadata-Version: 2.1
Name: komand
Version: 3.2.0
Summary: Komand Plugin SDK
Home-page: https://github.com/rapid7/komand-plugin-sdk-python
Author: Rapid7 Integrations Alliance
Author-email: integrationalliance@rapid7.com
License: UNKNOWN
Platform: UNKNOWN
Classifier: Programming Language :: Python :: 3
Classifier: Programming Language :: Python :: 2
Classifier: Operating System :: OS Independent
Classifier: Intended Audience :: Developers
Classifier: License :: OSI Approved :: MIT License
Classifier: Natural Language :: English
Classifier: Topic :: Software Development :: Build Tools
Requires-Dist: requests (>=2.20.0)
Requires-Dist: python-jsonschema-objects (==0.3.2)
Requires-Dist: jsonschema (==2.3.0)
Requires-Dist: certifi (==2017.11.5)
Requires-Dist: six (==1.11.0)
Requires-Dist: Flask (==0.12.3)
Requires-Dist: gunicorn (==19.7.1)
Requires-Dist: futures ; python_version == "2.7"
